sharepoint_utils/__init__.py
sharepoint_utils/basic_utils.py
sharepoint_utils/connection.py
sharepoint_utils/spreadsheet_utils.py
mpr_sharepoint_utils-2.0.5.dist-info/METADATA
mpr_sharepoint_utils-2.0.5.dist-info/WHEEL
mpr_sharepoint_utils-2.0.5.dist-info/top_level.txt
mpr_sharepoint_utils-2.0.5.dist-info/RECORD
