Metadata-Version: 2.1
Name: mpr-sharepoint-utils
Version: 2.0.5
Summary: A shared package for reading and writing to SharePoint
Author-email: Claire McShane <cmcshane@mathematica-mpr.com>, Holden Huntzinger <hhuntzinger@mathematica-mpr.com>, Max Grody <mgrody@mathematica-mpr.com>
Classifier: Programming Language :: Python :: 3
Classifier: License :: Free for non-commercial use
Classifier: Operating System :: OS Independent
Requires-Python: >=3.9
Requires-Dist: requests-ntlm
Provides-Extra: openpyxl
Requires-Dist: openpyxl ; extra == 'openpyxl'
Provides-Extra: pandas
Requires-Dist: pandas ; extra == 'pandas'
